pynotify/__init__.py
pynotify/pynotify.py
pynotify-0.1.1.dist-info/DESCRIPTION.rst
pynotify-0.1.1.dist-info/METADATA
pynotify-0.1.1.dist-info/RECORD
pynotify-0.1.1.dist-info/WHEEL
pynotify-0.1.1.dist-info/metadata.json
pynotify-0.1.1.dist-info/top_level.txt
